jiaxin/__init__.py
jiaxin/jiaxin.py
jx/__init__.py
jx/jiaxin.py
jiaxin-1.5.2.0.dist-info/LICENSE
jiaxin-1.5.2.0.dist-info/METADATA
jiaxin-1.5.2.0.dist-info/WHEEL
jiaxin-1.5.2.0.dist-info/top_level.txt
jiaxin-1.5.2.0.dist-info/RECORD
