Metadata-Version: 2.1
Name: jiaxin
Version: 1.5.2.0
Summary: i love jiaxin
Home-page: https://jiaxin.com
Author: yugong
Author-email: 923601132@qq.com
License: UNKNOWN
Platform: UNKNOWN
Classifier: Programming Language :: Python :: 3
Classifier: License :: OSI Approved :: MIT License
Classifier: Operating System :: OS Independent
